pwdgen/__init__.py
pwdgen/__main__.py
pwdgen/cli.py
pwdgen/helper.py
pwdgen/gen/pwd.py
pwdgen_py-1.1.3.dist-info/METADATA
pwdgen_py-1.1.3.dist-info/WHEEL
pwdgen_py-1.1.3.dist-info/entry_points.txt
pwdgen_py-1.1.3.dist-info/licenses/LICENSE
pwdgen_py-1.1.3.dist-info/RECORD
