Metadata-Version: 2.4
Name: pwdgen-py
Version: 1.1.3
Summary: A secure password generator
Project-URL: Source, https://github.com/mentiferous/pwdgen.git
Author: mentiferous
License-Expression: GPL-3.0-or-later
License-File: LICENSE
Keywords: generator,passwords,pwdgen,pwdgen-py
Classifier: Development Status :: 5 - Production/Stable
Classifier: Intended Audience :: End Users/Desktop
Classifier: License :: OSI Approved :: GNU General Public License v3 or later (GPLv3+)
Classifier: Natural Language :: English
Classifier: Operating System :: OS Independent
Classifier: Programming Language :: Python :: 3
Classifier: Programming Language :: Python :: 3 :: Only
Classifier: Programming Language :: Python :: 3.6
Classifier: Programming Language :: Python :: 3.7
Classifier: Programming Language :: Python :: 3.8
Classifier: Programming Language :: Python :: 3.9
Classifier: Programming Language :: Python :: 3.10
Classifier: Programming Language :: Python :: 3.11
Classifier: Programming Language :: Python :: 3.12
Classifier: Programming Language :: Python :: 3.13
Classifier: Topic :: Utilities
Requires-Python: >=3.6
Requires-Dist: rich
